zaphodtex/__init__.py
zaphodtex/zaphod.py
zaphodtex-0.7.0.dist-info/licenses/LICENSE
zaphodtex-0.7.0.dist-info/METADATA
zaphodtex-0.7.0.dist-info/WHEEL
zaphodtex-0.7.0.dist-info/entry_points.txt
zaphodtex-0.7.0.dist-info/top_level.txt
zaphodtex-0.7.0.dist-info/RECORD
