Metadata-Version: 2.4
Name: zaphodtex
Version: 0.7.0
Summary: A LaTeX change tracking tool
Home-page: https://github.com/sanjayankur31/zaphod
Author: Ankur Sinha
Author-email: ankursinha@fedoraproject.org
License: GPL-3.0-or-later
Classifier: Intended Audience :: Science/Research
Classifier: Natural Language :: English
Classifier: Operating System :: OS Independent
Classifier: Programming Language :: Python :: 3.9
Classifier: Programming Language :: Python :: 3.10
Classifier: Programming Language :: Python :: 3.11
Classifier: Programming Language :: Python :: 3.12
Classifier: Programming Language :: Python :: 3.13
Classifier: Topic :: Scientific/Engineering
License-File: LICENSE
Dynamic: license-file
